{"tipoD":"Doctorado","validacionD":"Pendiente","dateD":"20/1/2021","nombreD":"Angel Alejandro","apaternoD":"Sánchez","amaternoD":"Galicia","fechaD":"1000-03-03","lugarD":"MX","nacionalidadD":"MX","civilD":"CDMX","curpD":"SAGA000320HDFNLNA4","dependenciasD":"0","telefonoD":"5586939975","emailD":"alexsnz.20g@gmail.com","skypeD":"SDA","fbD":"FB","CalleD":"orquidea","NoExtD":"SN","NoIntD":"das","ColoniaD":"DASDA","CiudadD":"CDMX","EstadoD":"FDASDSA","CPD":"14650","InstitucionD":"dsadsa","pinstitucionD":"dasdas","InstitucionPosgradoD":"dasdas","pInstitucionPosgradoD":"dasdas","tituladoDoctoradoD":"si","xpPD":"a","xpDD":"a","propedeuticoD":"si","aniospropD":"1212","motivoD":"dasdsa","archivosubido1D":"Investigación IEEE.pdf","archivosubido2D":"Investigación HDLC y PPP.pdf","comentarioD":"Sin comentarios"}